passagemath_linbox/__init__.py
passagemath_linbox.libs/libfflas-627943ac.so.1.0.0
passagemath_linbox.libs/libffpack-2a5accbc.so.1.0.0
passagemath_linbox.libs/libflint-ea9ec694.so.22.0.0
passagemath_linbox.libs/libgd-76eb082b.so.3.0.11
passagemath_linbox.libs/libgfortran-83c28eba.so.5.0.0
passagemath_linbox.libs/libgivaro-5bc78711.so.9.2.1
passagemath_linbox.libs/libgmp-6e109695.so.10.5.0
passagemath_linbox.libs/libgmpxx-ecb9d6e3.so.4.7.0
passagemath_linbox.libs/libiml-aeb1d147.so.0.1.1
passagemath_linbox.libs/liblinbox-1a8bccec.so.0.0.0
passagemath_linbox.libs/libm4ri-1ab812bb.so.1.0.1
passagemath_linbox.libs/libm4rie-43f274a0.so.1.0.0
passagemath_linbox.libs/libmpfr-104d25bb.so.6.2.2
passagemath_linbox.libs/libopenblasp-r0-6dcb67f9.3.29.so
passagemath_linbox.libs/libpng16-b4a91cd1.so.16.43.0
passagemath_linbox.libs/libquadmath-2284e583.so.0.0.0
sage/all__sagemath_linbox.py
sage/geometry/all__sagemath_linbox.py
sage/geometry/integral_points.pxi
sage/geometry/integral_points_integer_dense.cpython-312-x86_64-linux-gnu.so
sage/geometry/integral_points_integer_dense.pyx
sage/libs/all__sagemath_linbox.py
sage/libs/iml.pxd
sage/libs/m4ri.pxd
sage/libs/m4rie.pxd
sage/libs/linbox/__init__.py
sage/libs/linbox/conversion.pxd
sage/libs/linbox/fflas.pxd
sage/libs/linbox/givaro.pxd
sage/libs/linbox/linbox.pxd
sage/libs/linbox/linbox_flint_interface.cpython-312-x86_64-linux-gnu.so
sage/libs/linbox/linbox_flint_interface.pxd
sage/libs/linbox/linbox_flint_interface.pyx
sage/matrix/all__sagemath_linbox.py
sage/matrix/matrix_cyclo_linbox.cpython-312-x86_64-linux-gnu.so
sage/matrix/matrix_cyclo_linbox.pyx
sage/matrix/matrix_gf2e_dense.cpython-312-x86_64-linux-gnu.so
sage/matrix/matrix_gf2e_dense.pxd
sage/matrix/matrix_gf2e_dense.pyx
sage/matrix/matrix_integer_iml.cpython-312-x86_64-linux-gnu.so
sage/matrix/matrix_integer_iml.pyx
sage/matrix/matrix_integer_linbox.cpython-312-x86_64-linux-gnu.so
sage/matrix/matrix_integer_linbox.pxd
passagemath_linbox-10.6.43.dist-info/METADATA
passagemath_linbox-10.6.43.dist-info/WHEEL
passagemath_linbox-10.6.43.dist-info/top_level.txt
passagemath_linbox-10.6.43.dist-info/RECORD
passagemath_linbox-10.6.43.dist-info/sboms/auditwheel.cdx.json
